README.md
setup.py
euclid_launcher.egg-info/PKG-INFO
euclid_launcher.egg-info/SOURCES.txt
euclid_launcher.egg-info/dependency_links.txt
euclid_launcher.egg-info/entry_points.txt
euclid_launcher.egg-info/requires.txt
euclid_launcher.egg-info/top_level.txt
src/__init__.py
src/main.py
src/utils.py