Metadata-Version: 2.1
Name: euclid-launcher
Version: 1.0.1
Summary: A commandline program for managing and launching projects.
Home-page: https://github.com/brenodega28/Euclid
Author: Breno Gomes
Author-email: brenodega28@gmail.com
License: MIT
Download-URL: https://github.com/brenodega28/Euclid/archive/v_01.tar.gz
Platform: UNKNOWN
Classifier: License :: OSI Approved :: MIT License
Classifier: Programming Language :: Python :: 2.7
Classifier: Programming Language :: Python :: 3
Classifier: Programming Language :: Python :: 3.7
Requires-Python: >=3
